agenthub/anthropic/__init__.py
agenthub/anthropic/core.py
agenthub/anthropic/types.py
agenthub/anthropic/util.py
agenthub/anthropic/repl/__init__.py
agenthub/anthropic/repl/repl.py
agenthub_anthropic-0.0.5.dist-info/METADATA
agenthub_anthropic-0.0.5.dist-info/WHEEL
agenthub_anthropic-0.0.5.dist-info/top_level.txt
agenthub_anthropic-0.0.5.dist-info/RECORD
